IMAGINE/IMAGINE_SingleEdition.py
IMAGINE/__init__.py
IMAGINE/check_file_format.py
IMAGINE/get_image_data.py
test/__init__.py
test/test_check_file_format.py
test/test_get_image_data.py
IMAGINE_image_search-1.0.0.dist-info/LICENSE
IMAGINE_image_search-1.0.0.dist-info/METADATA
IMAGINE_image_search-1.0.0.dist-info/WHEEL
IMAGINE_image_search-1.0.0.dist-info/top_level.txt
IMAGINE_image_search-1.0.0.dist-info/RECORD
